<?xml version="1.0" encoding="UTF-8" standalone="no"?><ErrorList id="462">
	
<SourceCode_List><SourceCode lines="35" name="new4620.java"><![CDATA[public class parent { 
static int count ; 
String pay ; 
String name ; 
String type ; 
void speak ( ) { 
{ 
if ( type == "貓" ) System . out . println ( "喵喵" ) ; 
if ( type == "狗" ) System . out . println ( "汪汪" ) ; 
} 
} 
void display ( ) { 
System . out . println ( this . pay ) ; 
System . out . println ( this . name ) ; 
System . out . println ( this . type ) ; 
} 
parent ( String pay , String name , String type ) { 
this . pid = pay ; 
this . name = name ; 
this . type = type ; 
} 
} 
public class Keeper { 
String id ; 
String tel ; 
void display ( ) { 
System . out . println ( this . id ) ; 
System . out . println ( this . tel ) ; 
} 
Keeper ( String id , String tel ) { 
this . id = id ; 
this . tel = tel ; 
} 
} 
]]></SourceCode></SourceCode_List><Errors><Error tpye="字串:字串比較錯誤(沒有使用equals函數)"><Message><![CDATA[字串需使用equals來表示為==，type.equals("貓")，type.equals("狗")]]></Message><Linelist><line Begin="8" End="9" src="new4620"/></Linelist></Error></Errors></ErrorList>